setup.py
distributions_test_450/Binomialdistribution.py
distributions_test_450/Gaussiandistribution.py
distributions_test_450/Generaldistribution.py
distributions_test_450/__init__.py
distributions_test_450.egg-info/PKG-INFO
distributions_test_450.egg-info/SOURCES.txt
distributions_test_450.egg-info/dependency_links.txt
distributions_test_450.egg-info/not-zip-safe
distributions_test_450.egg-info/top_level.txt