Metadata-Version: 1.0
Name: distributions-test-450
Version: 0.1
Summary: Gaussian and Binomial distributions
Home-page: UNKNOWN
Author: ['anonymous']
Author-email: UNKNOWN
License: UNKNOWN
Platform: UNKNOWN
